autolean/__init__.py
autolean-0.0.1.dist-info/licenses/LICENSE
autolean-0.0.1.dist-info/METADATA
autolean-0.0.1.dist-info/WHEEL
autolean-0.0.1.dist-info/top_level.txt
autolean-0.0.1.dist-info/RECORD
