Metadata-Version: 2.4
Name: autolean
Version: 0.0.1
Summary: Initial release forthcoming.
Author: Philipp Borchert
License-Expression: MIT
Project-URL: Homepage, https://github.com/pnborchert/autolean
Project-URL: Repository, https://github.com/pnborchert/autolean
Project-URL: Issues, https://github.com/pnborchert/autolean/issues
Keywords: autolean,placeholder
Classifier: Programming Language :: Python :: 3
Classifier: Operating System :: OS Independent
Requires-Python: >=3.9
License-File: LICENSE
Dynamic: license-file
